{"id": "7JL01", "name": "Hayling Island", "url_force": "http://www.hampshire.police.uk/internet/my-neighbourhood/havant/hayling-island/hayling-island/", "centre": {"latitude": "50.8057", "longitude": "-0.980719"}, "population": "0", "contact_details": {"email": "Hayling.Police@hampshire.pnn.police.uk", "telephone": "101"}, "links": [], "locations": [{"type": "station", "name": "Hayling island", "description": "<p>Opening Hours:<br />Mon: Closed<br />Tue: Closed<br />Wed: Closed<br />Thu: Closed<br />Fri: 0800 - 2000<br />Sat: 0800 - 2000<br />Sun: 0900 - 1400 &amp; 1445 - 1700</p>", "address": "Elm grove, Hayling Island", "postcode": "PO11 9EE", "latitude": null, "longitude": null}]}