{"id": "2SC01", "name": "Bevois", "url_force": "http://www.hampshire.police.uk/internet/my-neighbourhood//southampton/southampton-central/bevois/", "centre": {"latitude": "50.915", "longitude": "-1.39131"}, "population": "0", "contact_details": {"email": "Southampton.central.police@hampshire.police.uk", "telephone": "101"}, "links": [], "locations": [{"type": "station", "name": "Southampton Central", "description": "<p>Opening Hours:<br />Mon: 0800 - 2000<br />Tue: 0800 - 2000<br />Wed: 0800 - 2000<br />Thu: 0800 - 2000<br />Fri: 0800 - 2000<br />Sat: 0800 - 2000<br />Sun: 0800 - 2000</p>", "address": "Southampton Central Neighbourhood Team\nCivic Offices\nSouthampton\nHampshire", "postcode": "SO14 7LY", "latitude": null, "longitude": null}], "description": "<p>The Southampton Central Sector covers mainly residential areas and business/coastal areas of the central part of the city of Southampton.  This diverse area encompasses the beats of Newtown, Northam &amp; Bevois Valley.<br />The Bevois Neighbourhood Policing Team is here to provide a consistent presence and approach to any quality of life issue connected to crime and anti social behaviour.  Our team is dedicated to focussing on helping the most vulnerable residents &amp; targeting crime hot spots and prolific offenders.  <br />We provide a problem solving logic to the issues, and are committed to working alongside the community and statutory partners to make Southampton Central Sector a good place to live and work. <br />You will see the team of police officers and PCSO''s out on foot, on bikes and in vehicles providing an active presence in your neighbourhood.  Behind the scenes, we work together with our colleagues in the various teams, such as the Operation Fortress Team &amp; the Response and Patrol Team.</p>"}