{"id": "NC31", "name": "Boston Town West", "url_force": "", "centre": {"latitude": "52.9818", "longitude": "-0.044992"}, "population": "0", "contact_details": {"email": "boston@lincs.police.uk", "twitter": "https://twitter.com/bostonpoliceuk", "facebook": "https://www.facebook.com/BostonPoliceUK/", "unknown": "https://nextdoor.co.uk/agency-detail/england/lincolnshire/lincolnshire-police-boston/"}, "links": [], "locations": [{"type": "station", "name": "Boston Police Station", "description": null, "address": "Lincoln Lane, Boston", "postcode": "PE21 8QS", "latitude": null, "longitude": null}]}