{"id": "ES1NH8", "name": "Lewes Bridge", "url_force": "", "centre": {"latitude": "50.8766", "longitude": "0.0350497"}, "population": "296", "contact_details": {"email": "lewes@sussex.pnn.police.uk", "facebook": "https://www.facebook.com/LewesPolice/", "website": "www.sussex.police.uk", "telephone": "101"}, "links": [], "locations": [{"type": "station", "name": "Lewes Police Station", "description": null, "address": "6 North Street, Lewes", "postcode": "BN7 2PA", "latitude": "50.8745", "longitude": "0.0112278"}]}