{"id": "ER1NH3", "name": "St Marks", "url_force": "", "centre": {"latitude": "50.8435", "longitude": "0.411821"}, "population": "4631", "contact_details": {"email": "rother@sussex.pnn.police.uk", "twitter": "https://twitter.com/sussex_police", "facebook": "https://www.facebook.com/sussexpoliceforce"}, "links": [], "locations": [{"type": "station", "name": "Battle Police Station", "description": "<p>This police station front office is open Monday to Friday from 9am until 12 midday.</p>", "address": "North Trade Road, Battle", "postcode": "TN33 0EX", "latitude": "50.8409", "longitude": "0.464921"}], "description": "<p>This police station front office is open Monday to Friday from 9am until 12 midday.</p>"}