{"neighbourhood_id": "BE191", "neighbourhood_name": "Old City Docks", "force_id": "avon-and-somerset", "lat": "51.4521", "lng": "-2.59336", "population": 12098, "total_crimes": 1793, "categories": {"anti-social-behaviour": 297, "bicycle-theft": 35, "burglary": 99, "criminal-damage-arson": 102, "drugs": 42, "other-theft": 141, "possession-of-weapons": 7, "public-order": 153, "robbery": 59, "shoplifting": 135, "theft-from-the-person": 25, "vehicle-crime": 118, "violent-crime": 560, "other-crime": 20}, "date": "2026-01", "crime_rate_per_1000": 148.21}
