{"neighbourhood_id": "bar", "neighbourhood_name": "Barbican", "force_id": "city-of-london", "lat": "51.519", "lng": "-0.0926135", "population": "0", "total_crimes": 2309, "categories": {"anti-social-behaviour": 226, "bicycle-theft": 66, "burglary": 121, "criminal-damage-arson": 46, "drugs": 165, "other-theft": 438, "possession-of-weapons": 9, "public-order": 123, "robbery": 70, "shoplifting": 302, "theft-from-the-person": 333, "vehicle-crime": 59, "violent-crime": 341, "other-crime": 10}, "date": "2026-01"}