{"neighbourhood_id": "E05009855", "neighbourhood_name": "Berwick Hills and Pallister", "force_id": "cleveland", "lat": "54.5598", "lng": "-1.20347", "population": 9227, "total_crimes": 604, "categories": {"anti-social-behaviour": 63, "bicycle-theft": 1, "burglary": 32, "criminal-damage-arson": 68, "drugs": 31, "other-theft": 34, "possession-of-weapons": 3, "public-order": 49, "robbery": 11, "shoplifting": 37, "theft-from-the-person": 4, "vehicle-crime": 21, "violent-crime": 227, "other-crime": 23}, "date": "2026-01", "crime_rate_per_1000": 65.46}
