{"neighbourhood_id": "E05009392", "neighbourhood_name": "Colville", "force_id": "metropolitan", "lat": "51.5158", "lng": "-0.204507", "population": "0", "total_crimes": 1691, "categories": {"anti-social-behaviour": 373, "bicycle-theft": 19, "burglary": 94, "criminal-damage-arson": 59, "drugs": 39, "other-theft": 144, "possession-of-weapons": 8, "public-order": 84, "robbery": 40, "shoplifting": 257, "theft-from-the-person": 90, "vehicle-crime": 105, "violent-crime": 365, "other-crime": 14}, "date": "2026-01"}