{"neighbourhood_id": "E05009393", "neighbourhood_name": "Courtfield", "force_id": "metropolitan", "lat": "51.4913", "lng": "-0.1814", "population": "0", "total_crimes": 1354, "categories": {"anti-social-behaviour": 244, "bicycle-theft": 19, "burglary": 70, "criminal-damage-arson": 58, "drugs": 63, "other-theft": 150, "possession-of-weapons": 4, "public-order": 68, "robbery": 22, "shoplifting": 132, "theft-from-the-person": 91, "vehicle-crime": 104, "violent-crime": 315, "other-crime": 14}, "date": "2026-01"}