{"neighbourhood_id": "E05013531", "neighbourhood_name": "Northolt Mandeville", "force_id": "metropolitan", "lat": "51.5486", "lng": "-0.374264", "population": 16844, "total_crimes": 278, "categories": {"anti-social-behaviour": 56, "bicycle-theft": 1, "burglary": 20, "criminal-damage-arson": 12, "drugs": 20, "other-theft": 13, "possession-of-weapons": 1, "public-order": 9, "robbery": 5, "shoplifting": 10, "theft-from-the-person": 10, "vehicle-crime": 27, "violent-crime": 89, "other-crime": 5}, "date": "2026-01", "crime_rate_per_1000": 16.5}
